tessif_oemof_4_4/__init__.py
tessif_oemof_4_4/optimize.py
tessif_oemof_4_4/post_process.py
tessif_oemof_4_4/transform.py
tessif_oemof_4_4-0.1.10.dist-info/LICENSE
tessif_oemof_4_4-0.1.10.dist-info/WHEEL
tessif_oemof_4_4-0.1.10.dist-info/METADATA
tessif_oemof_4_4-0.1.10.dist-info/RECORD
