Metadata-Version: 2.1
Name: tessif-oemof-4-4
Version: 0.1.10
Summary: Tessif-Plugin for providing oemof version 4.4. support.
Home-page: https://github.com/tZ3ma/tessif_oemof_4_4
License: MIT
Keywords: Tessif,Tessif-Oemof,tessif-oemof,ESSMOS,optimization,energy supply system modelling
Author: Mathias Ammon
Author-email: tz3ma.coding@use.startmail.com
Requires-Python: >=3.8,<4.0
Classifier: License :: OSI Approved :: MIT License
Classifier: Programming Language :: Python :: 3
Classifier: Programming Language :: Python :: 3.8
Classifier: Programming Language :: Python :: 3.9
Classifier: Programming Language :: Python :: 3.10
Classifier: Programming Language :: Python :: 3.11
Requires-Dist: oemof-solph (==0.4.4)
Requires-Dist: tessif (>=0.0.27)
Project-URL: Repository, https://github.com/tZ3ma/tessif_oemof_4_4
